ncbi/__init__.py
ncbi_cdonel-0.1.7.dist-info/licenses/LICENSE
ncbi_cdonel-0.1.7.dist-info/METADATA
ncbi_cdonel-0.1.7.dist-info/WHEEL
ncbi_cdonel-0.1.7.dist-info/top_level.txt
ncbi_cdonel-0.1.7.dist-info/RECORD
