Metadata-Version: 2.4
Name: ncbi_cdonel
Version: 0.1.7
Summary: A set of tools to retrieve NCBI records.
Author-email: Cory Donelson <coryjdonelson@gmail.com>
Project-URL: Homepage, https://github.com/cdonel/ncbi
Requires-Python: >=3.9
License-File: LICENSE
Requires-Dist: biopython>=1.85
Dynamic: license-file
